naint/__init__.py
naint/client.py
naint/speech_to_text.py
naint/text_to_speech.py
naint/types.py
naint/voice_cloning.py
naint/voices.py
naint-0.2.3.dist-info/METADATA
naint-0.2.3.dist-info/WHEEL
naint-0.2.3.dist-info/top_level.txt
naint-0.2.3.dist-info/RECORD
