Metadata-Version: 2.4
Name: naint
Version: 0.2.3
Summary: Python client for NAINT API
Author-email: Anton Poponin <ajhtcn9@gmail.com>
Requires-Python: >=3.12
Requires-Dist: httpx>=0.28.1
Requires-Dist: pydantic>=2.11.5
Requires-Dist: numpy>=2.2.6
Requires-Dist: scipy>=1.15.3
Requires-Dist: librosa>=0.11.0
Requires-Dist: soundfile>=0.13.1
